core_sentry/__init__.py
core_sentry/py.typed
core_sentry/decorators/__init__.py
core_sentry/decorators/base.py
core_sentry/tests/__init__.py
core_sentry/tests/base.py
core_sentry-1.0.1.dist-info/licenses/LICENSE
core_sentry-1.0.1.dist-info/METADATA
core_sentry-1.0.1.dist-info/WHEEL
core_sentry-1.0.1.dist-info/top_level.txt
core_sentry-1.0.1.dist-info/RECORD
