Metadata-Version: 2.4
Name: core-sentry
Version: 1.0.1
Summary: This project provides common components related to the integration with Sentry...
Author-email: Alejandro Cora González <alek.cora.glez@gmail.com>
Maintainer: Alejandro Cora González
License-Expression: MIT
Project-URL: Homepage, https://gitlab.com/bytecode-solutions/core/core-sentry
Project-URL: Repository, https://gitlab.com/bytecode-solutions/core/core-sentry
Project-URL: Documentation, https://core-sentry.readthedocs.io/en/latest/
Project-URL: Issues, https://gitlab.com/bytecode-solutions/core/core-sentry/-/issues
Project-URL: Changelog, https://gitlab.com/bytecode-solutions/core/core-sentry/-/blob/master/CHANGELOG.md
Classifier: Intended Audience :: Developers
Classifier: Development Status :: 5 - Production/Stable
Classifier: Topic :: Software Development :: Libraries :: Python Modules
Classifier: Topic :: Utilities
Classifier: Programming Language :: Python
Classifier: Programming Language :: Python :: 3
Classifier: Programming Language :: Python :: 3 :: Only
Classifier: Programming Language :: Python :: 3.9
Classifier: Programming Language :: Python :: 3.10
Classifier: Programming Language :: Python :: 3.11
Classifier: Programming Language :: Python :: 3.12
Classifier: Programming Language :: Python :: 3.13
Requires-Python: >=3.9
License-File: LICENSE
Requires-Dist: core-tests>=2.0.2
Requires-Dist: sentry-sdk>=2.29.1
Provides-Extra: dev
Requires-Dist: core-dev-tools>=1.0.1; extra == "dev"
Dynamic: license-file
